sbrowser/__init__.py
sbrowser/sbrowser.py
scraping_browser-0.2.4.dist-info/LICENSE
scraping_browser-0.2.4.dist-info/METADATA
scraping_browser-0.2.4.dist-info/WHEEL
scraping_browser-0.2.4.dist-info/top_level.txt
scraping_browser-0.2.4.dist-info/RECORD
