Metadata-Version: 2.1
Name: scraping-browser
Version: 0.2.4
Summary: Web-Scraping browser emulator
Home-page: https://gibraltar.chi.uni-hannover.de/pflug/browser
Author: Fabian Pflug
Author-email: pflug@chi.uni-hannover.de
License: UNKNOWN
Platform: UNKNOWN
Classifier: Programming Language :: Python :: 3
Classifier: License :: OSI Approved :: MIT License
Classifier: Operating System :: OS Independent
Requires-Dist: requests
